langda/__init__.py
langda/config.py
langda/database.py
langda/logger.py
langda/agent/__init__.py
langda/agent/evaluate_nodes.py
langda/agent/general_nodes.py
langda/agent/generate_nodes.py
langda/agent/langda_agent.py
langda/agent/requirements_builder.py
langda/agent/state.py
langda/prompts/Problog_Syntax.txt
langda/prompts/evaluate_prompt_doublechain.txt
langda/prompts/evaluate_prompt_react.txt
langda/prompts/evaluate_prompt_simple.txt
langda/prompts/generate_prompt_doublechain.txt
langda/prompts/generate_prompt_react.txt
langda/prompts/generate_prompt_simple.txt
langda/prompts/regenerate_prompt_doublechain.txt
langda/prompts/regenerate_prompt_react.txt
langda/prompts/regenerate_prompt_simple.txt
langda/prompts/zfinaltest_prompt_simple.txt
langda/utils/__init__.py
langda/utils/agent_tools.py
langda/utils/format_tools.py
langda/utils/models.py
langda/utils/parser_v2.py
langda/utils/problog_docs.json
langda/utils/test_tools.py
langda/utils/vector_store_v4.py
langda-0.0.1.dist-info/licenses/LICENSE
langda-0.0.1.dist-info/METADATA
langda-0.0.1.dist-info/WHEEL
langda-0.0.1.dist-info/top_level.txt
langda-0.0.1.dist-info/RECORD
