Metadata-Version: 2.4
Name: langda
Version: 0.0.1
Summary: A Python package for semi-formal modeling in neuro-symbolic systems.
Home-page: 
Author: Simon Kohaut
Author-email: simon-kohaut@cs.tu-darmstadt.de
Classifier: Programming Language :: Python :: 3
Classifier: License :: OSI Approved :: BSD License
Classifier: Operating System :: OS Independent
Requires-Python: >=3.10
License-File: LICENSE
Requires-Dist: langgraph>=0.4.3
Requires-Dist: pydantic>=2.11.4
Requires-Dist: pydantic-settings>=2.9.1
Requires-Dist: problog
Requires-Dist: langchain>=0.3.25
Requires-Dist: langchain-community>=0.3.24
Requires-Dist: langchain-core>=0.3.59
Requires-Dist: langchain-deepseek>=0.1.3
Requires-Dist: langchain-groq>=0.3.2
Requires-Dist: langchain-openai>=0.3.16
Requires-Dist: python-dotenv>=1.1.0
Provides-Extra: faiss
Requires-Dist: faiss-cpu>=1.7.4; extra == "faiss"
Provides-Extra: faiss-gpu
Requires-Dist: faiss-gpu>=1.7.4; extra == "faiss-gpu"
Provides-Extra: dev
Requires-Dist: tqdm>=4.65.0; extra == "dev"
Provides-Extra: telegram
Requires-Dist: python-telegram-bot>=22.0; extra == "telegram"
Dynamic: author
Dynamic: author-email
Dynamic: classifier
Dynamic: description
Dynamic: description-content-type
Dynamic: license-file
Dynamic: provides-extra
Dynamic: requires-dist
Dynamic: requires-python
Dynamic: summary
